[1,0,0,[["cc.AnimationClip",["_name","curveData"],1]],[[0,0,1,3]],[[0,"level38-finish",{"paths":{"object/Win":{"props":{"active":[{"frame":0,"value":true}]}},"object/FG":{"props":{"active":[{"frame":0,"value":false}]}},"object/incorrect_Eyes":{"props":{"active":[{"frame":0,"value":false}]}},"object/Tower":{"props":{"active":[{"frame":0,"value":false}]}},"object/correct":{"props":{"active":[{"frame":0,"value":false}]}},"object/BG":{"props":{"active":[{"frame":0,"value":false}]}},"object/incorrect_ArmR":{"comps":{},"props":{"active":[{"frame":0,"value":false}]}},"object/incorrect_W":{"comps":{},"props":{"active":[{"frame":0,"value":false}]}},"object/incorrect_ArmL":{"comps":{},"props":{"active":[{"frame":0,"value":false}]}}}}]],0,0,[],[],[]]